fuzzytail/__init__.py
fuzzytail/__main__.py
fuzzytail/cli/__init__.py
fuzzytail/cli/builds.py
fuzzytail/cli/logs.py
fuzzytail/cli/main.py
fuzzytail/cli/watch.py
fuzzytail/models/__init__.py
fuzzytail/models/build.py
fuzzytail/services/__init__.py
fuzzytail/services/copr.py
fuzzytail/services/logs.py
fuzzytail/ui/__init__.py
fuzzytail/ui/display.py
fuzzytail/ui/panels.py
fuzzytail/ui/tui.py
fuzzytail-0.2.0.dist-info/METADATA
fuzzytail-0.2.0.dist-info/WHEEL
fuzzytail-0.2.0.dist-info/entry_points.txt
fuzzytail-0.2.0.dist-info/licenses/LICENSE
fuzzytail-0.2.0.dist-info/RECORD
